<mujoco model="terrain_scene">
  <compiler angle="radian" coordinate="local" inertiafromgeom="true" />
  <option timestep="0.002" gravity="0.0 0.0 -9.81" iterations="50" solver="Newton" />
  <visual>
    <global offwidth="1920" offheight="1080" />
    <quality shadowsize="4096" />
    <headlight ambient="0.4 0.4 0.4" diffuse="0.6 0.6 0.6" />
  </visual>
  <asset>
    <texture name="grid_texture" type="2d" builtin="checker" rgb1="0.9 0.9 0.9" rgb2="0.7 0.7 0.7" width="512" height="512" />
    <material name="grid_material" texture="grid_texture" texrepeat="10 10" reflectance="0.1" />
  </asset>
  <worldbody>
    <geom name="ground" type="plane" size="6.0 6.0 0.1" pos="0 0 0" rgba="0.8 0.8 0.8 1.0" friction="1.0 0.005 0.0001" />
    <geom name="box_0" type="box" size="0.2814 0.2203 0.0100" pos="-2.7500 -2.7500 0.0100" rgba="0.200 0.200 0.200 1.000" friction="1.0 0.005 0.0001" />
    <geom name="box_1" type="box" size="0.1793 0.2462 0.0212" pos="-2.7500 -2.2500 0.0212" rgba="0.357 0.357 0.357 1.000" friction="1.0 0.005 0.0001" />
    <geom name="box_2" type="box" size="0.1592 0.2929 0.0360" pos="-2.7500 -1.7500 0.0360" rgba="0.564 0.564 0.564 1.000" friction="1.0 0.005 0.0001" />
    <geom name="box_3" type="box" size="0.2718 0.2061 0.0512" pos="-2.7500 -1.2500 0.0512" rgba="0.777 0.777 0.777 1.000" friction="1.0 0.005 0.0001" />
    <geom name="box_4" type="box" size="0.2019 0.1788 0.0216" pos="-2.7500 -0.7500 0.0216" rgba="0.363 0.363 0.363 1.000" friction="1.0 0.005 0.0001" />
    <geom name="box_5" type="box" size="0.2804 0.2344 0.0381" pos="-2.7500 -0.2500 0.0381" rgba="0.593 0.593 0.593 1.000" friction="1.0 0.005 0.0001" />
    <geom name="box_6" type="box" size="0.1938 0.1696 0.0217" pos="-2.7500 0.2500 0.0217" rgba="0.364 0.364 0.364 1.000" friction="1.0 0.005 0.0001" />
    <geom name="box_7" type="box" size="0.1567 0.2408 0.0323" pos="-2.7500 0.7500 0.0323" rgba="0.512 0.512 0.512 1.000" friction="1.0 0.005 0.0001" />
    <geom name="box_8" type="box" size="0.1508 0.2438 0.0437" pos="-2.7500 1.2500 0.0437" rgba="0.671 0.671 0.671 1.000" friction="1.0 0.005 0.0001" />
    <geom name="box_9" type="box" size="0.1631 0.2587 0.0326" pos="-2.7500 1.7500 0.0326" rgba="0.516 0.516 0.516 1.000" friction="1.0 0.005 0.0001" />
    <geom name="box_10" type="box" size="0.2168 0.1900 0.0415" pos="-2.7500 2.2500 0.0415" rgba="0.641 0.641 0.641 1.000" friction="1.0 0.005 0.0001" />
    <geom name="box_11" type="box" size="0.2681 0.2510 0.0311" pos="-2.7500 2.7500 0.0311" rgba="0.495 0.495 0.495 1.000" friction="1.0 0.005 0.0001" />
    <geom name="box_12" type="box" size="0.2176 0.1914 0.0508" pos="-2.2500 -2.7500 0.0508" rgba="0.772 0.772 0.772 1.000" friction="1.0 0.005 0.0001" />
    <geom name="box_13" type="box" size="0.2037 0.2530 0.0439" pos="-2.2500 -2.2500 0.0439" rgba="0.674 0.674 0.674 1.000" friction="1.0 0.005 0.0001" />
    <geom name="box_14" type="box" size="0.2024 0.2764 0.0426" pos="-2.2500 -1.7500 0.0426" rgba="0.656 0.656 0.656 1.000" friction="1.0 0.005 0.0001" />
    <geom name="box_15" type="box" size="0.1806 0.2080 0.0140" pos="-2.2500 -1.2500 0.0140" rgba="0.256 0.256 0.256 1.000" friction="1.0 0.005 0.0001" />
    <geom name="box_16" type="box" size="0.1692 0.2193 0.0367" pos="-2.2500 -0.7500 0.0367" rgba="0.574 0.574 0.574 1.000" friction="1.0 0.005 0.0001" />
    <geom name="box_17" type="box" size="0.2987 0.2162 0.0396" pos="-2.2500 -0.2500 0.0396" rgba="0.614 0.614 0.614 1.000" friction="1.0 0.005 0.0001" />
    <geom name="box_18" type="box" size="0.1576 0.2714 0.0295" pos="-2.2500 0.2500 0.0295" rgba="0.473 0.473 0.473 1.000" friction="1.0 0.005 0.0001" />
    <geom name="box_19" type="box" size="0.1850 0.1845 0.0230" pos="-2.2500 0.7500 0.0230" rgba="0.383 0.383 0.383 1.000" friction="1.0 0.005 0.0001" />
    <geom name="box_20" type="box" size="0.2348 0.2142 0.0119" pos="-2.2500 1.2500 0.0119" rgba="0.226 0.226 0.226 1.000" friction="1.0 0.005 0.0001" />
    <geom name="box_21" type="box" size="0.1644 0.2050 0.0384" pos="-2.2500 1.7500 0.0384" rgba="0.598 0.598 0.598 1.000" friction="1.0 0.005 0.0001" />
    <geom name="box_22" type="box" size="0.1511 0.2690 0.0100" pos="-2.2500 2.2500 0.0100" rgba="0.200 0.200 0.200 1.000" friction="1.0 0.005 0.0001" />
    <geom name="box_23" type="box" size="0.2674 0.1974 0.0278" pos="-2.2500 2.7500 0.0278" rgba="0.449 0.449 0.449 1.000" friction="1.0 0.005 0.0001" />
    <geom name="box_24" type="box" size="0.2696 0.2405 0.0213" pos="-1.7500 -2.7500 0.0213" rgba="0.358 0.358 0.358 1.000" friction="1.0 0.005 0.0001" />
    <geom name="box_25" type="box" size="0.1923 0.1586 0.0342" pos="-1.7500 -2.2500 0.0342" rgba="0.539 0.539 0.539 1.000" friction="1.0 0.005 0.0001" />
    <geom name="box_26" type="box" size="0.2730 0.1909 0.0557" pos="-1.7500 -1.7500 0.0557" rgba="0.840 0.840 0.840 1.000" friction="1.0 0.005 0.0001" />
    <geom name="box_27" type="box" size="0.2737 0.1521 0.0196" pos="-1.7500 -1.2500 0.0196" rgba="0.334 0.334 0.334 1.000" friction="1.0 0.005 0.0001" />
    <geom name="box_28" type="box" size="0.2764 0.2070 0.0376" pos="-1.7500 -0.7500 0.0376" rgba="0.586 0.586 0.586 1.000" friction="1.0 0.005 0.0001" />
    <geom name="box_29" type="box" size="0.2004 0.1922 0.0443" pos="-1.7500 -0.2500 0.0443" rgba="0.680 0.680 0.680 1.000" friction="1.0 0.005 0.0001" />
    <geom name="box_30" type="box" size="0.1680 0.2809 0.0296" pos="-1.7500 0.2500 0.0296" rgba="0.474 0.474 0.474 1.000" friction="1.0 0.005 0.0001" />
    <geom name="box_31" type="box" size="0.2706 0.1826 0.0188" pos="-1.7500 0.7500 0.0188" rgba="0.323 0.323 0.323 1.000" friction="1.0 0.005 0.0001" />
    <geom name="box_32" type="box" size="0.2766 0.1671 0.0433" pos="-1.7500 1.2500 0.0433" rgba="0.667 0.667 0.667 1.000" friction="1.0 0.005 0.0001" />
    <geom name="box_33" type="box" size="0.1705 0.2476 0.0230" pos="-1.7500 1.7500 0.0230" rgba="0.382 0.382 0.382 1.000" friction="1.0 0.005 0.0001" />
    <geom name="box_34" type="box" size="0.1664 0.2040 0.0158" pos="-1.7500 2.2500 0.0158" rgba="0.281 0.281 0.281 1.000" friction="1.0 0.005 0.0001" />
    <geom name="box_35" type="box" size="0.2401 0.2286 0.0188" pos="-1.7500 2.7500 0.0188" rgba="0.323 0.323 0.323 1.000" friction="1.0 0.005 0.0001" />
    <geom name="box_36" type="box" size="0.1974 0.1603 0.0598" pos="-1.2500 -2.7500 0.0598" rgba="0.897 0.897 0.897 1.000" friction="1.0 0.005 0.0001" />
    <geom name="box_37" type="box" size="0.1961 0.2196 0.0371" pos="-1.2500 -2.2500 0.0371" rgba="0.580 0.580 0.580 1.000" friction="1.0 0.005 0.0001" />
    <geom name="box_38" type="box" size="0.1707 0.2118 0.0492" pos="-1.2500 -1.7500 0.0492" rgba="0.749 0.749 0.749 1.000" friction="1.0 0.005 0.0001" />
    <geom name="box_39" type="box" size="0.1630 0.2220 0.0143" pos="-1.2500 -1.2500 0.0143" rgba="0.260 0.260 0.260 1.000" friction="1.0 0.005 0.0001" />
    <geom name="box_40" type="box" size="0.1978 0.2771 0.0555" pos="-1.2500 -0.7500 0.0555" rgba="0.837 0.837 0.837 1.000" friction="1.0 0.005 0.0001" />
    <geom name="box_41" type="box" size="0.1885 0.2827 0.0260" pos="-1.2500 -0.2500 0.0260" rgba="0.424 0.424 0.424 1.000" friction="1.0 0.005 0.0001" />
    <geom name="box_42" type="box" size="0.2325 0.2959 0.0461" pos="-1.2500 0.2500 0.0461" rgba="0.705 0.705 0.705 1.000" friction="1.0 0.005 0.0001" />
    <geom name="box_43" type="box" size="0.2124 0.2217 0.0582" pos="-1.2500 0.7500 0.0582" rgba="0.875 0.875 0.875 1.000" friction="1.0 0.005 0.0001" />
    <geom name="box_44" type="box" size="0.2181 0.1873 0.0213" pos="-1.2500 1.2500 0.0213" rgba="0.358 0.358 0.358 1.000" friction="1.0 0.005 0.0001" />
    <geom name="box_45" type="box" size="0.1821 0.2305 0.0595" pos="-1.2500 1.7500 0.0595" rgba="0.893 0.893 0.893 1.000" friction="1.0 0.005 0.0001" />
    <geom name="box_46" type="box" size="0.1576 0.1787 0.0504" pos="-1.2500 2.2500 0.0504" rgba="0.765 0.765 0.765 1.000" friction="1.0 0.005 0.0001" />
    <geom name="box_47" type="box" size="0.1775 0.1808 0.0306" pos="-1.2500 2.7500 0.0306" rgba="0.489 0.489 0.489 1.000" friction="1.0 0.005 0.0001" />
    <geom name="box_48" type="box" size="0.2242 0.1547 0.0392" pos="-0.7500 -2.7500 0.0392" rgba="0.609 0.609 0.609 1.000" friction="1.0 0.005 0.0001" />
    <geom name="box_49" type="box" size="0.2657 0.2165 0.0257" pos="-0.7500 -2.2500 0.0257" rgba="0.419 0.419 0.419 1.000" friction="1.0 0.005 0.0001" />
    <geom name="box_50" type="box" size="0.1897 0.2518 0.0531" pos="-0.7500 -1.7500 0.0531" rgba="0.804 0.804 0.804 1.000" friction="1.0 0.005 0.0001" />
    <geom name="box_51" type="box" size="0.2560 0.2476 0.0332" pos="-0.7500 -1.2500 0.0332" rgba="0.524 0.524 0.524 1.000" friction="1.0 0.005 0.0001" />
    <geom name="box_52" type="box" size="0.2111 0.1906 0.0461" pos="-0.7500 1.2500 0.0461" rgba="0.705 0.705 0.705 1.000" friction="1.0 0.005 0.0001" />
    <geom name="box_53" type="box" size="0.2861 0.1555 0.0303" pos="-0.7500 1.7500 0.0303" rgba="0.484 0.484 0.484 1.000" friction="1.0 0.005 0.0001" />
    <geom name="box_54" type="box" size="0.1840 0.2191 0.0297" pos="-0.7500 2.2500 0.0297" rgba="0.475 0.475 0.475 1.000" friction="1.0 0.005 0.0001" />
    <geom name="box_55" type="box" size="0.2938 0.1872 0.0130" pos="-0.7500 2.7500 0.0130" rgba="0.241 0.241 0.241 1.000" friction="1.0 0.005 0.0001" />
    <geom name="box_56" type="box" size="0.2956 0.2504 0.0391" pos="-0.2500 -2.7500 0.0391" rgba="0.607 0.607 0.607 1.000" friction="1.0 0.005 0.0001" />
    <geom name="box_57" type="box" size="0.2745 0.2172 0.0481" pos="-0.2500 -2.2500 0.0481" rgba="0.733 0.733 0.733 1.000" friction="1.0 0.005 0.0001" />
    <geom name="box_58" type="box" size="0.1833 0.1864 0.0362" pos="-0.2500 -1.7500 0.0362" rgba="0.566 0.566 0.566 1.000" friction="1.0 0.005 0.0001" />
    <geom name="box_59" type="box" size="0.2810 0.2092 0.0395" pos="-0.2500 -1.2500 0.0395" rgba="0.613 0.613 0.613 1.000" friction="1.0 0.005 0.0001" />
    <geom name="box_60" type="box" size="0.2221 0.1673 0.0347" pos="-0.2500 1.2500 0.0347" rgba="0.546 0.546 0.546 1.000" friction="1.0 0.005 0.0001" />
    <geom name="box_61" type="box" size="0.2569 0.2212 0.0439" pos="-0.2500 1.7500 0.0439" rgba="0.674 0.674 0.674 1.000" friction="1.0 0.005 0.0001" />
    <geom name="box_62" type="box" size="0.1806 0.2607 0.0241" pos="-0.2500 2.2500 0.0241" rgba="0.397 0.397 0.397 1.000" friction="1.0 0.005 0.0001" />
    <geom name="box_63" type="box" size="0.2583 0.2631 0.0310" pos="-0.2500 2.7500 0.0310" rgba="0.494 0.494 0.494 1.000" friction="1.0 0.005 0.0001" />
    <geom name="box_64" type="box" size="0.1571 0.2197 0.0225" pos="0.2500 -2.7500 0.0225" rgba="0.376 0.376 0.376 1.000" friction="1.0 0.005 0.0001" />
    <geom name="box_65" type="box" size="0.2053 0.2158 0.0449" pos="0.2500 -2.2500 0.0449" rgba="0.689 0.689 0.689 1.000" friction="1.0 0.005 0.0001" />
    <geom name="box_66" type="box" size="0.1543 0.2989 0.0301" pos="0.2500 -1.7500 0.0301" rgba="0.481 0.481 0.481 1.000" friction="1.0 0.005 0.0001" />
    <geom name="box_67" type="box" size="0.1737 0.2198 0.0225" pos="0.2500 -1.2500 0.0225" rgba="0.375 0.375 0.375 1.000" friction="1.0 0.005 0.0001" />
    <geom name="box_68" type="box" size="0.2011 0.2347 0.0390" pos="0.2500 1.2500 0.0390" rgba="0.605 0.605 0.605 1.000" friction="1.0 0.005 0.0001" />
    <geom name="box_69" type="box" size="0.2882 0.2098 0.0105" pos="0.2500 1.7500 0.0105" rgba="0.207 0.207 0.207 1.000" friction="1.0 0.005 0.0001" />
    <geom name="box_70" type="box" size="0.2149 0.2294 0.0485" pos="0.2500 2.2500 0.0485" rgba="0.739 0.739 0.739 1.000" friction="1.0 0.005 0.0001" />
    <geom name="box_71" type="box" size="0.2392 0.1528 0.0379" pos="0.2500 2.7500 0.0379" rgba="0.591 0.591 0.591 1.000" friction="1.0 0.005 0.0001" />
    <geom name="box_72" type="box" size="0.1577 0.1852 0.0533" pos="0.7500 -2.7500 0.0533" rgba="0.806 0.806 0.806 1.000" friction="1.0 0.005 0.0001" />
    <geom name="box_73" type="box" size="0.1514 0.2975 0.0104" pos="0.7500 -2.2500 0.0104" rgba="0.206 0.206 0.206 1.000" friction="1.0 0.005 0.0001" />
    <geom name="box_74" type="box" size="0.1911 0.2052 0.0207" pos="0.7500 -1.7500 0.0207" rgba="0.349 0.349 0.349 1.000" friction="1.0 0.005 0.0001" />
    <geom name="box_75" type="box" size="0.2869 0.2658 0.0419" pos="0.7500 -1.2500 0.0419" rgba="0.647 0.647 0.647 1.000" friction="1.0 0.005 0.0001" />
    <geom name="box_76" type="box" size="0.2795 0.2167 0.0218" pos="0.7500 1.2500 0.0218" rgba="0.365 0.365 0.365 1.000" friction="1.0 0.005 0.0001" />
    <geom name="box_77" type="box" size="0.2246 0.1571 0.0377" pos="0.7500 1.7500 0.0377" rgba="0.588 0.588 0.588 1.000" friction="1.0 0.005 0.0001" />
    <geom name="box_78" type="box" size="0.2318 0.1760 0.0274" pos="0.7500 2.2500 0.0274" rgba="0.443 0.443 0.443 1.000" friction="1.0 0.005 0.0001" />
    <geom name="box_79" type="box" size="0.2859 0.2495 0.0521" pos="0.7500 2.7500 0.0521" rgba="0.790 0.790 0.790 1.000" friction="1.0 0.005 0.0001" />
    <geom name="box_80" type="box" size="0.2633 0.2010 0.0456" pos="1.2500 -2.7500 0.0456" rgba="0.699 0.699 0.699 1.000" friction="1.0 0.005 0.0001" />
    <geom name="box_81" type="box" size="0.2384 0.1947 0.0256" pos="1.2500 -2.2500 0.0256" rgba="0.419 0.419 0.419 1.000" friction="1.0 0.005 0.0001" />
    <geom name="box_82" type="box" size="0.2104 0.2448 0.0471" pos="1.2500 -1.7500 0.0471" rgba="0.719 0.719 0.719 1.000" friction="1.0 0.005 0.0001" />
    <geom name="box_83" type="box" size="0.2289 0.2672 0.0324" pos="1.2500 -1.2500 0.0324" rgba="0.513 0.513 0.513 1.000" friction="1.0 0.005 0.0001" />
    <geom name="box_84" type="box" size="0.1562 0.1575 0.0182" pos="1.2500 -0.7500 0.0182" rgba="0.314 0.314 0.314 1.000" friction="1.0 0.005 0.0001" />
    <geom name="box_85" type="box" size="0.1731 0.2598 0.0243" pos="1.2500 -0.2500 0.0243" rgba="0.400 0.400 0.400 1.000" friction="1.0 0.005 0.0001" />
    <geom name="box_86" type="box" size="0.2154 0.1712 0.0496" pos="1.2500 0.2500 0.0496" rgba="0.755 0.755 0.755 1.000" friction="1.0 0.005 0.0001" />
    <geom name="box_87" type="box" size="0.2789 0.2416 0.0444" pos="1.2500 0.7500 0.0444" rgba="0.681 0.681 0.681 1.000" friction="1.0 0.005 0.0001" />
    <geom name="box_88" type="box" size="0.2385 0.2677 0.0214" pos="1.2500 1.2500 0.0214" rgba="0.360 0.360 0.360 1.000" friction="1.0 0.005 0.0001" />
    <geom name="box_89" type="box" size="0.2039 0.2575 0.0468" pos="1.2500 1.7500 0.0468" rgba="0.715 0.715 0.715 1.000" friction="1.0 0.005 0.0001" />
    <geom name="box_90" type="box" size="0.2202 0.1590 0.0340" pos="1.2500 2.2500 0.0340" rgba="0.535 0.535 0.535 1.000" friction="1.0 0.005 0.0001" />
    <geom name="box_91" type="box" size="0.2474 0.2483 0.0236" pos="1.2500 2.7500 0.0236" rgba="0.391 0.391 0.391 1.000" friction="1.0 0.005 0.0001" />
    <geom name="box_92" type="box" size="0.2281 0.2441 0.0187" pos="1.7500 -2.7500 0.0187" rgba="0.322 0.322 0.322 1.000" friction="1.0 0.005 0.0001" />
    <geom name="box_93" type="box" size="0.1956 0.1722 0.0100" pos="1.7500 -2.2500 0.0100" rgba="0.200 0.200 0.200 1.000" friction="1.0 0.005 0.0001" />
    <geom name="box_94" type="box" size="0.1568 0.1800 0.0332" pos="1.7500 -1.7500 0.0332" rgba="0.524 0.524 0.524 1.000" friction="1.0 0.005 0.0001" />
    <geom name="box_95" type="box" size="0.1863 0.2728 0.0140" pos="1.7500 -1.2500 0.0140" rgba="0.257 0.257 0.257 1.000" friction="1.0 0.005 0.0001" />
    <geom name="box_96" type="box" size="0.2015 0.2826 0.0440" pos="1.7500 -0.7500 0.0440" rgba="0.676 0.676 0.676 1.000" friction="1.0 0.005 0.0001" />
    <geom name="box_97" type="box" size="0.2013 0.2573 0.0429" pos="1.7500 -0.2500 0.0429" rgba="0.660 0.660 0.660 1.000" friction="1.0 0.005 0.0001" />
    <geom name="box_98" type="box" size="0.2927 0.2953 0.0349" pos="1.7500 0.2500 0.0349" rgba="0.548 0.548 0.548 1.000" friction="1.0 0.005 0.0001" />
    <geom name="box_99" type="box" size="0.1518 0.2856 0.0343" pos="1.7500 0.7500 0.0343" rgba="0.540 0.540 0.540 1.000" friction="1.0 0.005 0.0001" />
    <geom name="box_100" type="box" size="0.1710 0.2793 0.0559" pos="1.7500 1.2500 0.0559" rgba="0.843 0.843 0.843 1.000" friction="1.0 0.005 0.0001" />
    <geom name="box_101" type="box" size="0.2786 0.1888 0.0536" pos="1.7500 1.7500 0.0536" rgba="0.811 0.811 0.811 1.000" friction="1.0 0.005 0.0001" />
    <geom name="box_102" type="box" size="0.2564 0.1925 0.0217" pos="1.7500 2.2500 0.0217" rgba="0.364 0.364 0.364 1.000" friction="1.0 0.005 0.0001" />
    <geom name="box_103" type="box" size="0.1768 0.1594 0.0517" pos="1.7500 2.7500 0.0517" rgba="0.784 0.784 0.784 1.000" friction="1.0 0.005 0.0001" />
    <geom name="box_104" type="box" size="0.2713 0.2820 0.0418" pos="2.2500 -2.7500 0.0418" rgba="0.645 0.645 0.645 1.000" friction="1.0 0.005 0.0001" />
    <geom name="box_105" type="box" size="0.2493 0.1550 0.0160" pos="2.2500 -2.2500 0.0160" rgba="0.284 0.284 0.284 1.000" friction="1.0 0.005 0.0001" />
    <geom name="box_106" type="box" size="0.1725 0.2375 0.0276" pos="2.2500 -1.7500 0.0276" rgba="0.447 0.447 0.447 1.000" friction="1.0 0.005 0.0001" />
    <geom name="box_107" type="box" size="0.2899 0.2088 0.0131" pos="2.2500 -1.2500 0.0131" rgba="0.244 0.244 0.244 1.000" friction="1.0 0.005 0.0001" />
    <geom name="box_108" type="box" size="0.1536 0.2716 0.0273" pos="2.2500 -0.7500 0.0273" rgba="0.443 0.443 0.443 1.000" friction="1.0 0.005 0.0001" />
    <geom name="box_109" type="box" size="0.1786 0.2860 0.0545" pos="2.2500 -0.2500 0.0545" rgba="0.824 0.824 0.824 1.000" friction="1.0 0.005 0.0001" />
    <geom name="box_110" type="box" size="0.2412 0.2881 0.0430" pos="2.2500 0.2500 0.0430" rgba="0.662 0.662 0.662 1.000" friction="1.0 0.005 0.0001" />
    <geom name="box_111" type="box" size="0.2766 0.2967 0.0445" pos="2.2500 0.7500 0.0445" rgba="0.683 0.683 0.683 1.000" friction="1.0 0.005 0.0001" />
    <geom name="box_112" type="box" size="0.2312 0.2135 0.0413" pos="2.2500 1.2500 0.0413" rgba="0.638 0.638 0.638 1.000" friction="1.0 0.005 0.0001" />
    <geom name="box_113" type="box" size="0.2257 0.2843 0.0464" pos="2.2500 1.7500 0.0464" rgba="0.710 0.710 0.710 1.000" friction="1.0 0.005 0.0001" />
    <geom name="box_114" type="box" size="0.1821 0.2320 0.0169" pos="2.2500 2.2500 0.0169" rgba="0.297 0.297 0.297 1.000" friction="1.0 0.005 0.0001" />
    <geom name="box_115" type="box" size="0.1869 0.2179 0.0489" pos="2.2500 2.7500 0.0489" rgba="0.745 0.745 0.745 1.000" friction="1.0 0.005 0.0001" />
    <geom name="box_116" type="box" size="0.1921 0.1743 0.0259" pos="2.7500 -2.7500 0.0259" rgba="0.422 0.422 0.422 1.000" friction="1.0 0.005 0.0001" />
    <geom name="box_117" type="box" size="0.2776 0.2655 0.0238" pos="2.7500 -2.2500 0.0238" rgba="0.394 0.394 0.394 1.000" friction="1.0 0.005 0.0001" />
    <geom name="box_118" type="box" size="0.2102 0.2136 0.0350" pos="2.7500 -1.7500 0.0350" rgba="0.550 0.550 0.550 1.000" friction="1.0 0.005 0.0001" />
    <geom name="box_119" type="box" size="0.2039 0.1826 0.0600" pos="2.7500 -1.2500 0.0600" rgba="0.900 0.900 0.900 1.000" friction="1.0 0.005 0.0001" />
    <geom name="box_120" type="box" size="0.2274 0.2249 0.0486" pos="2.7500 -0.7500 0.0486" rgba="0.740 0.740 0.740 1.000" friction="1.0 0.005 0.0001" />
    <geom name="box_121" type="box" size="0.2185 0.2556 0.0369" pos="2.7500 -0.2500 0.0369" rgba="0.577 0.577 0.577 1.000" friction="1.0 0.005 0.0001" />
    <geom name="box_122" type="box" size="0.1966 0.2211 0.0506" pos="2.7500 0.2500 0.0506" rgba="0.769 0.769 0.769 1.000" friction="1.0 0.005 0.0001" />
    <geom name="box_123" type="box" size="0.2532 0.1622 0.0126" pos="2.7500 0.7500 0.0126" rgba="0.237 0.237 0.237 1.000" friction="1.0 0.005 0.0001" />
    <geom name="box_124" type="box" size="0.2891 0.2755 0.0501" pos="2.7500 1.2500 0.0501" rgba="0.761 0.761 0.761 1.000" friction="1.0 0.005 0.0001" />
    <geom name="box_125" type="box" size="0.1930 0.1784 0.0434" pos="2.7500 1.7500 0.0434" rgba="0.667 0.667 0.667 1.000" friction="1.0 0.005 0.0001" />
    <geom name="box_126" type="box" size="0.1922 0.2340 0.0257" pos="2.7500 2.2500 0.0257" rgba="0.420 0.420 0.420 1.000" friction="1.0 0.005 0.0001" />
    <geom name="box_127" type="box" size="0.1542 0.1819 0.0559" pos="2.7500 2.7500 0.0559" rgba="0.842 0.842 0.842 1.000" friction="1.0 0.005 0.0001" />
    <light name="main_light" pos="0 0 5" dir="0 0 -1" diffuse="0.6 0.6 0.6" specular="0.3 0.3 0.3" castshadow="true" />
    <camera name="track_cam" mode="trackcom" pos="3.0 0 2" xyaxes="0 1 0 -0.5 0 1" />
    <camera name="overview" pos="5 5 8" quat="0.5 0.5 -0.5 -0.5" />
  </worldbody>
</mujoco>
